{ "_id" : { "$oid" : "586cd621641694232165c16c" }, "imageUrl" : "pasta-salad.jpg", "name" : "Salads", "enteredBy" : "demo", "templateName" : "foodDemoApp", "appId" : "586cd621641694232165c16b", "createdAt" : { "$date" : "2017-01-04T16:31:53.431+0530" }, "updatedAt" : { "$date" : "2017-01-04T16:31:53.431+0530" } }
{ "_id" : { "$oid" : "586cd621641694232165c16d" }, "imageUrl" : "crpes.jpg", "name" : "Deserts", "enteredBy" : "demo", "templateName" : "foodDemoApp", "appId" : "586cd621641694232165c16b", "createdAt" : { "$date" : "2017-01-04T16:31:53.432+0530" }, "updatedAt" : { "$date" : "2017-01-04T16:31:53.432+0530" } }
{ "_id" : { "$oid" : "586cd621641694232165c16e" }, "imageUrl" : "how-to-grill-fish.jpg", "name" : "Stakes", "enteredBy" : "demo", "templateName" : "foodDemoApp", "appId" : "586cd621641694232165c16b", "createdAt" : { "$date" : "2017-01-04T16:31:53.432+0530" }, "updatedAt" : { "$date" : "2017-01-04T16:31:53.432+0530" } }
{ "_id" : { "$oid" : "586cd62b641694232165c177" }, "imageUrl" : "shirt_x.png", "name" : "Shirt", "enteredBy" : "demo", "templateName" : "foodDemoApp2", "appId" : "586cd62b641694232165c176", "createdAt" : { "$date" : "2017-01-04T16:32:03.012+0530" }, "updatedAt" : { "$date" : "2017-01-04T16:32:03.012+0530" } }
{ "_id" : { "$oid" : "586cd62b641694232165c178" }, "imageUrl" : "short_x.png", "name" : "Short", "enteredBy" : "demo", "templateName" : "foodDemoApp2", "appId" : "586cd62b641694232165c176", "createdAt" : { "$date" : "2017-01-04T16:32:03.012+0530" }, "updatedAt" : { "$date" : "2017-01-04T16:32:03.012+0530" } }
{ "_id" : { "$oid" : "586cd62b641694232165c179" }, "imageUrl" : "cloth3.png", "name" : "Suits", "enteredBy" : "demo", "templateName" : "foodDemoApp2", "appId" : "586cd62b641694232165c176", "createdAt" : { "$date" : "2017-01-04T16:32:03.014+0530" }, "updatedAt" : { "$date" : "2017-01-04T16:32:03.014+0530" } }
{ "_id" : { "$oid" : "586cd633641694232165c180" }, "imageUrl" : "a.png", "name" : "Women Shoes", "enteredBy" : "demo", "templateName" : "clothingApp", "appId" : "586cd633641694232165c17f", "createdAt" : { "$date" : "2017-01-04T16:32:11.994+0530" }, "updatedAt" : { "$date" : "2017-01-04T16:32:11.994+0530" } }
{ "_id" : { "$oid" : "586cd633641694232165c181" }, "imageUrl" : "c.png", "name" : "Men Shirts", "enteredBy" : "demo", "templateName" : "clothingApp", "appId" : "586cd633641694232165c17f", "createdAt" : { "$date" : "2017-01-04T16:32:11.994+0530" }, "updatedAt" : { "$date" : "2017-01-04T16:32:11.994+0530" } }
{ "_id" : { "$oid" : "586cd633641694232165c182" }, "imageUrl" : "d.png", "name" : "Men Shoes", "enteredBy" : "demo", "templateName" : "clothingApp", "appId" : "586cd633641694232165c17f", "createdAt" : { "$date" : "2017-01-04T16:32:11.994+0530" }, "updatedAt" : { "$date" : "2017-01-04T16:32:11.994+0530" } }
{ "_id" : { "$oid" : "586cd633641694232165c183" }, "imageUrl" : "cloth3.png", "name" : "Accessories", "enteredBy" : "demo", "templateName" : "clothingApp", "appId" : "586cd633641694232165c17f", "createdAt" : { "$date" : "2017-01-04T16:32:11.995+0530" }, "updatedAt" : { "$date" : "2017-01-04T16:32:11.995+0530" } }
{ "_id" : { "$oid" : "586cd641641694232165c18d" }, "imageUrl" : "1.JPG", "name" : "Accessories", "enteredBy" : "demo", "templateName" : "GlamourUpApp", "appId" : "586cd641641694232165c18c", "createdAt" : { "$date" : "2017-01-04T16:32:25.259+0530" }, "updatedAt" : { "$date" : "2017-01-04T16:32:25.259+0530" } }
{ "_id" : { "$oid" : "586cd641641694232165c18e" }, "imageUrl" : "2.JPG", "name" : "Women Tops", "enteredBy" : "demo", "templateName" : "GlamourUpApp", "appId" : "586cd641641694232165c18c", "createdAt" : { "$date" : "2017-01-04T16:32:25.259+0530" }, "updatedAt" : { "$date" : "2017-01-04T16:32:25.259+0530" } }
{ "_id" : { "$oid" : "586cd641641694232165c18f" }, "imageUrl" : "3.JPG", "name" : "Dresses", "enteredBy" : "demo", "templateName" : "GlamourUpApp", "appId" : "586cd641641694232165c18c", "createdAt" : { "$date" : "2017-01-04T16:32:25.260+0530" }, "updatedAt" : { "$date" : "2017-01-04T16:32:25.260+0530" } }
{ "_id" : { "$oid" : "586cd641641694232165c190" }, "imageUrl" : "4.JPG", "name" : "Shoes", "enteredBy" : "demo", "templateName" : "GlamourUpApp", "appId" : "586cd641641694232165c18c", "createdAt" : { "$date" : "2017-01-04T16:32:25.261+0530" }, "updatedAt" : { "$date" : "2017-01-04T16:32:25.261+0530" } }
{ "_id" : { "$oid" : "586cd655641694232165c19d" }, "imageUrl" : "1.JPG", "name" : "New Arrivals", "enteredBy" : "demo", "templateName" : "CrushApp", "appId" : "586cd655641694232165c19c", "createdAt" : { "$date" : "2017-01-04T16:32:45.238+0530" }, "updatedAt" : { "$date" : "2017-01-04T16:32:45.238+0530" } }
{ "_id" : { "$oid" : "586cd655641694232165c19e" }, "imageUrl" : "2.JPG", "name" : "Surf", "enteredBy" : "demo", "templateName" : "CrushApp", "appId" : "586cd655641694232165c19c", "createdAt" : { "$date" : "2017-01-04T16:32:45.238+0530" }, "updatedAt" : { "$date" : "2017-01-04T16:32:45.238+0530" } }
{ "_id" : { "$oid" : "586cd655641694232165c19f" }, "imageUrl" : "3.JPG", "name" : "Men", "enteredBy" : "demo", "templateName" : "CrushApp", "appId" : "586cd655641694232165c19c", "createdAt" : { "$date" : "2017-01-04T16:32:45.239+0530" }, "updatedAt" : { "$date" : "2017-01-04T16:32:45.239+0530" } }
{ "_id" : { "$oid" : "586cd655641694232165c1a0" }, "imageUrl" : "4.JPG", "name" : "Women", "enteredBy" : "demo", "templateName" : "CrushApp", "appId" : "586cd655641694232165c19c", "createdAt" : { "$date" : "2017-01-04T16:32:45.239+0530" }, "updatedAt" : { "$date" : "2017-01-04T16:32:45.239+0530" } }
{ "_id" : { "$oid" : "586cd655641694232165c1a1" }, "imageUrl" : "5.JPG", "name" : "Kids", "enteredBy" : "demo", "templateName" : "CrushApp", "appId" : "586cd655641694232165c19c", "createdAt" : { "$date" : "2017-01-04T16:32:45.239+0530" }, "updatedAt" : { "$date" : "2017-01-04T16:32:45.239+0530" } }
{ "_id" : { "$oid" : "586cd65e641694232165c1b2" }, "imageUrl" : "1.JPG", "name" : "B&O Earphones", "enteredBy" : "demo", "templateName" : "HeadphoneApp", "appId" : "586cd65e641694232165c1b1", "createdAt" : { "$date" : "2017-01-04T16:32:54.918+0530" }, "updatedAt" : { "$date" : "2017-01-04T16:32:54.918+0530" } }
{ "_id" : { "$oid" : "586cd65e641694232165c1b3" }, "imageUrl" : "2.JPG", "name" : "B&O Bluetooth", "enteredBy" : "demo", "templateName" : "HeadphoneApp", "appId" : "586cd65e641694232165c1b1", "createdAt" : { "$date" : "2017-01-04T16:32:54.919+0530" }, "updatedAt" : { "$date" : "2017-01-04T16:32:54.919+0530" } }
{ "_id" : { "$oid" : "586cd65e641694232165c1b4" }, "imageUrl" : "3.JPG", "name" : "B&O Wall Speakers", "enteredBy" : "demo", "templateName" : "HeadphoneApp", "appId" : "586cd65e641694232165c1b1", "createdAt" : { "$date" : "2017-01-04T16:32:54.919+0530" }, "updatedAt" : { "$date" : "2017-01-04T16:32:54.919+0530" } }
{ "_id" : { "$oid" : "586cd65e641694232165c1b5" }, "imageUrl" : "4.JPG", "name" : "B&O Headphones", "enteredBy" : "demo", "templateName" : "HeadphoneApp", "appId" : "586cd65e641694232165c1b1", "createdAt" : { "$date" : "2017-01-04T16:32:54.920+0530" }, "updatedAt" : { "$date" : "2017-01-04T16:32:54.920+0530" } }
{ "_id" : { "$oid" : "586cd65e641694232165c1b6" }, "imageUrl" : "5.JPG", "name" : "B&O Speakers", "enteredBy" : "demo", "templateName" : "HeadphoneApp", "appId" : "586cd65e641694232165c1b1", "createdAt" : { "$date" : "2017-01-04T16:32:54.921+0530" }, "updatedAt" : { "$date" : "2017-01-04T16:32:54.921+0530" } }
{ "_id" : { "$oid" : "586cd66a641694232165c1c7" }, "name" : "Large Pizza", "imageUrl" : "category_01.png", "enteredBy" : "demo", "templateName" : "ECommerceApp", "appId" : "586cd66a641694232165c1c6", "createdAt" : { "$date" : "2017-01-04T16:33:06.452+0530" }, "updatedAt" : { "$date" : "2017-01-04T16:33:06.452+0530" } }
{ "_id" : { "$oid" : "586cd66a641694232165c1c8" }, "name" : "Indian Pizza", "imageUrl" : "category_02.png", "enteredBy" : "demo", "templateName" : "ECommerceApp", "appId" : "586cd66a641694232165c1c6", "createdAt" : { "$date" : "2017-01-04T16:33:06.453+0530" }, "updatedAt" : { "$date" : "2017-01-04T16:33:06.453+0530" } }
{"_id":{"$oid":"587cb44c4d711ab806743d0e"},"name":"Women's","imageUrl":"category_01.png","enteredBy":"demo","templateName":"BondiApp","appId":"587cb44c4d711ab806743d0d","createdAt":{"$date":"2017-01-16T11:53:48.644Z"},"updatedAt":{"$date":"2017-01-16T11:53:48.644Z"}}
{"_id":{"$oid":"587cb44c4d711ab806743d0f"},"name":"Men's","imageUrl":"category_02.png","enteredBy":"demo","templateName":"BondiApp","appId":"587cb44c4d711ab806743d0d","createdAt":{"$date":"2017-01-16T11:53:48.646Z"},"updatedAt":{"$date":"2017-01-16T11:53:48.646Z"}}
{"_id":{"$oid":"587cb44c4d711ab806743d10"},"name":"Kid's","imageUrl":"category_03.png","enteredBy":"demo","templateName":"BondiApp","appId":"587cb44c4d711ab806743d0d","createdAt":{"$date":"2017-01-16T11:53:48.647Z"},"updatedAt":{"$date":"2017-01-16T11:53:48.647Z"}}
{"_id":{"$oid":"5881d10735d8f098239b2f6a"},"imageUrl":"a.png","name":"Stakes","enteredBy":"demo","templateName":"CatenitApp","appId":"5881d10735d8f098239b2f69","createdAt":{"$date":"2017-01-20T08:57:43.733Z"},"updatedAt":{"$date":"2017-01-20T08:57:43.733Z"}}
{"_id":{"$oid":"5881d10735d8f098239b2f6b"},"imageUrl":"c.png","name":"Deserts","enteredBy":"demo","templateName":"CatenitApp","appId":"5881d10735d8f098239b2f69","createdAt":{"$date":"2017-01-20T08:57:43.733Z"},"updatedAt":{"$date":"2017-01-20T08:57:43.733Z"}}
{"_id":{"$oid":"5881d10735d8f098239b2f6c"},"imageUrl":"d.png","name":"Beverages","enteredBy":"demo","templateName":"CatenitApp","appId":"5881d10735d8f098239b2f69","createdAt":{"$date":"2017-01-20T08:57:43.734Z"},"updatedAt":{"$date":"2017-01-20T08:57:43.734Z"}}
{"_id":{"$oid":"5881d10735d8f098239b2f6d"},"imageUrl":"cloth3.png","name":"Soups","enteredBy":"demo","templateName":"CatenitApp","appId":"5881d10735d8f098239b2f69","createdAt":{"$date":"2017-01-20T08:57:43.734Z"},"updatedAt":{"$date":"2017-01-20T08:57:43.734Z"}}
{"_id":{"$oid":"588866686602492c0519344d"},"imageUrl":"3.png","name":"Deserts","enteredBy":"demo","templateName":"DeliciousApp","appId":"588866686602492c05193449","createdAt":{"$date":"2017-01-25T08:48:40.424Z"},"updatedAt":{"$date":"2017-01-25T08:48:40.424Z"}}
{"_id":{"$oid":"588866686602492c0519344b"},"imageUrl":"2.png","name":"Soups","enteredBy":"demo","templateName":"DeliciousApp","appId":"588866686602492c05193449","createdAt":{"$date":"2017-01-25T08:48:40.423Z"},"updatedAt":{"$date":"2017-01-25T08:48:40.423Z"}}
{"_id":{"$oid":"588866686602492c0519344c"},"imageUrl":"1.png","name":"Salads","enteredBy":"demo","templateName":"DeliciousApp","appId":"588866686602492c05193449","createdAt":{"$date":"2017-01-25T08:48:40.424Z"},"updatedAt":{"$date":"2017-01-25T08:48:40.424Z"}}
{"_id":{"$oid":"588866686602492c0519344a"},"imageUrl":"4.png","name":"Main Course","enteredBy":"demo","templateName":"DeliciousApp","appId":"588866686602492c05193449","createdAt":{"$date":"2017-01-25T08:48:40.422Z"},"updatedAt":{"$date":"2017-01-25T08:48:40.422Z"}}
